{
    "/js/app.js": "/js/app.js",
    "/css/app.css": "/css/app.css",
    "/js/app.612cbf234721965146b4.hot-update.js": "/js/app.612cbf234721965146b4.hot-update.js",
    "/js/app.ecc1635b25a37a82c7fa.hot-update.js": "/js/app.ecc1635b25a37a82c7fa.hot-update.js",
    "/js/app.bcccf17e3b6677b6e38a.hot-update.js": "/js/app.bcccf17e3b6677b6e38a.hot-update.js",
    "/js/app.948ef3a06efe4aa55def.hot-update.js": "/js/app.948ef3a06efe4aa55def.hot-update.js",
    "/js/app.27ea935bfe86931e7d70.hot-update.js": "/js/app.27ea935bfe86931e7d70.hot-update.js",
    "/js/app.10a0d1a52604ac0134e3.hot-update.js": "/js/app.10a0d1a52604ac0134e3.hot-update.js",
    "/js/app.4c419e2af0a4c25cab7a.hot-update.js": "/js/app.4c419e2af0a4c25cab7a.hot-update.js",
    "/js/app.639e335c6f611ab30395.hot-update.js": "/js/app.639e335c6f611ab30395.hot-update.js",
    "/js/app.74044cffdbe848de93b2.hot-update.js": "/js/app.74044cffdbe848de93b2.hot-update.js",
    "/js/app.89115fa2ce68c79e92ca.hot-update.js": "/js/app.89115fa2ce68c79e92ca.hot-update.js",
    "/js/app.df449aa46663a6ed4646.hot-update.js": "/js/app.df449aa46663a6ed4646.hot-update.js",
    "/js/app.cb8a083ae67967b1cfa0.hot-update.js": "/js/app.cb8a083ae67967b1cfa0.hot-update.js",
    "/js/app.d37c454156696e4b06c8.hot-update.js": "/js/app.d37c454156696e4b06c8.hot-update.js",
    "/js/app.e051ea7efcb14223cbb2.hot-update.js": "/js/app.e051ea7efcb14223cbb2.hot-update.js",
    "/js/app.352536bbb260333c35a4.hot-update.js": "/js/app.352536bbb260333c35a4.hot-update.js",
    "/js/app.69723d3db835c2dc50c7.hot-update.js": "/js/app.69723d3db835c2dc50c7.hot-update.js",
    "/js/app.b793d21ae8664f8df6cd.hot-update.js": "/js/app.b793d21ae8664f8df6cd.hot-update.js",
    "/js/app.aff148a2c5c4ec4b136b.hot-update.js": "/js/app.aff148a2c5c4ec4b136b.hot-update.js",
    "/js/app.6df4d8550c64cdc5c170.hot-update.js": "/js/app.6df4d8550c64cdc5c170.hot-update.js",
    "/js/app.29b5307c15df7937e8e9.hot-update.js": "/js/app.29b5307c15df7937e8e9.hot-update.js",
    "/js/app.3951eeffbd3881059408.hot-update.js": "/js/app.3951eeffbd3881059408.hot-update.js",
    "/js/app.26367fca099c8040beb4.hot-update.js": "/js/app.26367fca099c8040beb4.hot-update.js",
    "/js/app.7f0bc52888541efaab36.hot-update.js": "/js/app.7f0bc52888541efaab36.hot-update.js",
    "/js/app.e996753962248a372175.hot-update.js": "/js/app.e996753962248a372175.hot-update.js",
    "/js/app.ee4b914424386c889d3d.hot-update.js": "/js/app.ee4b914424386c889d3d.hot-update.js",
    "/js/app.7d9d923f6108dc250c91.hot-update.js": "/js/app.7d9d923f6108dc250c91.hot-update.js",
    "/js/app.f6e7135b54d552134ba3.hot-update.js": "/js/app.f6e7135b54d552134ba3.hot-update.js",
    "/js/app.39aea815e78a4cb754cc.hot-update.js": "/js/app.39aea815e78a4cb754cc.hot-update.js",
    "/js/app.e76a944257b82954b90e.hot-update.js": "/js/app.e76a944257b82954b90e.hot-update.js",
    "/js/app.ddf603385bb5c53c8c59.hot-update.js": "/js/app.ddf603385bb5c53c8c59.hot-update.js",
    "/js/app.ab8930afe11b98356919.hot-update.js": "/js/app.ab8930afe11b98356919.hot-update.js",
    "/js/app.eac8da961d6b7a275262.hot-update.js": "/js/app.eac8da961d6b7a275262.hot-update.js",
    "/js/app.3155e39132536cba780c.hot-update.js": "/js/app.3155e39132536cba780c.hot-update.js",
    "/js/app.0c980345387c065fcb7e.hot-update.js": "/js/app.0c980345387c065fcb7e.hot-update.js",
    "/js/app.e0ea1af46ebddfc78d8b.hot-update.js": "/js/app.e0ea1af46ebddfc78d8b.hot-update.js",
    "/js/app.56ef8f9b8657261eca8c.hot-update.js": "/js/app.56ef8f9b8657261eca8c.hot-update.js",
    "/js/app.2bd465408e897e4aa212.hot-update.js": "/js/app.2bd465408e897e4aa212.hot-update.js",
    "/js/app.fe3c17ab6afc594fba84.hot-update.js": "/js/app.fe3c17ab6afc594fba84.hot-update.js",
    "/js/app.adc14e8bbe8014bdc881.hot-update.js": "/js/app.adc14e8bbe8014bdc881.hot-update.js",
    "/js/app.b9c8f97fe02d9fa8b782.hot-update.js": "/js/app.b9c8f97fe02d9fa8b782.hot-update.js",
    "/js/app.8a6066af45530049eb45.hot-update.js": "/js/app.8a6066af45530049eb45.hot-update.js",
    "/js/app.0a214457c90296c3e037.hot-update.js": "/js/app.0a214457c90296c3e037.hot-update.js",
    "/js/app.356a81b0dda64c4c0898.hot-update.js": "/js/app.356a81b0dda64c4c0898.hot-update.js",
    "/js/app.f7957c70f9ac98672b9e.hot-update.js": "/js/app.f7957c70f9ac98672b9e.hot-update.js",
    "/js/app.3d5d7cbf505b48a54888.hot-update.js": "/js/app.3d5d7cbf505b48a54888.hot-update.js",
    "/js/app.023278d77a965d5e989c.hot-update.js": "/js/app.023278d77a965d5e989c.hot-update.js",
    "/js/app.07141233bab275bb4d14.hot-update.js": "/js/app.07141233bab275bb4d14.hot-update.js",
    "/js/app.0bfcc9000e6396e79b59.hot-update.js": "/js/app.0bfcc9000e6396e79b59.hot-update.js",
    "/js/app.f0bb33a0028b21b7147a.hot-update.js": "/js/app.f0bb33a0028b21b7147a.hot-update.js",
    "/js/app.32defec2ab4692d05dd2.hot-update.js": "/js/app.32defec2ab4692d05dd2.hot-update.js",
    "/js/app.6a5935aec274c302422d.hot-update.js": "/js/app.6a5935aec274c302422d.hot-update.js",
    "/js/app.0e2613ae375c34f12610.hot-update.js": "/js/app.0e2613ae375c34f12610.hot-update.js",
    "/js/app.a9fabb5a3e183293c72d.hot-update.js": "/js/app.a9fabb5a3e183293c72d.hot-update.js",
    "/js/app.aa5ca5befb8c7b7a9f74.hot-update.js": "/js/app.aa5ca5befb8c7b7a9f74.hot-update.js",
    "/js/app.cd4580dd6e16979a6a5c.hot-update.js": "/js/app.cd4580dd6e16979a6a5c.hot-update.js",
    "/js/app.bc4b5252f503e2d31e39.hot-update.js": "/js/app.bc4b5252f503e2d31e39.hot-update.js",
    "/js/app.53ebbc1a64f5bd3d1eb6.hot-update.js": "/js/app.53ebbc1a64f5bd3d1eb6.hot-update.js",
    "/js/app.ecbdb9c14fc97718270c.hot-update.js": "/js/app.ecbdb9c14fc97718270c.hot-update.js",
    "/js/app.497e405b1667bb5d111c.hot-update.js": "/js/app.497e405b1667bb5d111c.hot-update.js",
    "/js/app.5f410c620fc31fd4b4c3.hot-update.js": "/js/app.5f410c620fc31fd4b4c3.hot-update.js",
    "/js/app.9eb0c208851fbccea940.hot-update.js": "/js/app.9eb0c208851fbccea940.hot-update.js",
    "/js/app.a4bbb7fec129ae739453.hot-update.js": "/js/app.a4bbb7fec129ae739453.hot-update.js",
    "/js/app.802f5aa1daad1b92cf23.hot-update.js": "/js/app.802f5aa1daad1b92cf23.hot-update.js",
    "/js/app.0873847a58ea97c9e3ba.hot-update.js": "/js/app.0873847a58ea97c9e3ba.hot-update.js",
    "/js/app.f33e5bff572d63a0bb21.hot-update.js": "/js/app.f33e5bff572d63a0bb21.hot-update.js",
    "/js/app.b31510ca9d683eec7a28.hot-update.js": "/js/app.b31510ca9d683eec7a28.hot-update.js",
    "/js/app.c625d8b281604a5b08cd.hot-update.js": "/js/app.c625d8b281604a5b08cd.hot-update.js",
    "/js/app.addebe888e92926b33e7.hot-update.js": "/js/app.addebe888e92926b33e7.hot-update.js",
    "/js/app.dbe4d98156108e2f44e0.hot-update.js": "/js/app.dbe4d98156108e2f44e0.hot-update.js",
    "/js/app.8c536ecd72f093c45002.hot-update.js": "/js/app.8c536ecd72f093c45002.hot-update.js",
    "/js/app.0802f46b518c7a7a1f83.hot-update.js": "/js/app.0802f46b518c7a7a1f83.hot-update.js",
    "/js/app.3afdf08122f95fca70a1.hot-update.js": "/js/app.3afdf08122f95fca70a1.hot-update.js",
    "/js/app.2abf6c4d22ec248e2bf2.hot-update.js": "/js/app.2abf6c4d22ec248e2bf2.hot-update.js",
    "/js/app.010aa239baae6f60d4e4.hot-update.js": "/js/app.010aa239baae6f60d4e4.hot-update.js",
    "/js/app.d8c24560399d4e309927.hot-update.js": "/js/app.d8c24560399d4e309927.hot-update.js",
    "/js/app.7eb382fac516c1657d56.hot-update.js": "/js/app.7eb382fac516c1657d56.hot-update.js",
    "/js/app.c2ad36903cad40373645.hot-update.js": "/js/app.c2ad36903cad40373645.hot-update.js",
    "/js/app.7bc539a934f85787bf60.hot-update.js": "/js/app.7bc539a934f85787bf60.hot-update.js",
    "/js/app.bbd5e1080033def9558b.hot-update.js": "/js/app.bbd5e1080033def9558b.hot-update.js",
    "/js/app.cc6afb916ce40956d1ca.hot-update.js": "/js/app.cc6afb916ce40956d1ca.hot-update.js",
    "/js/app.c1516ff787a72121c9eb.hot-update.js": "/js/app.c1516ff787a72121c9eb.hot-update.js",
    "/js/app.41ab34a9e38eefc6c356.hot-update.js": "/js/app.41ab34a9e38eefc6c356.hot-update.js",
    "/js/app.4974030d51b0518bb30d.hot-update.js": "/js/app.4974030d51b0518bb30d.hot-update.js",
    "/js/app.377ab407c9ab18d88822.hot-update.js": "/js/app.377ab407c9ab18d88822.hot-update.js",
    "/js/app.928946b1b05ef51df50f.hot-update.js": "/js/app.928946b1b05ef51df50f.hot-update.js",
    "/js/app.1a6c69a03ae02c9e4fed.hot-update.js": "/js/app.1a6c69a03ae02c9e4fed.hot-update.js",
    "/js/app.3dec4d761531d1e7fe8c.hot-update.js": "/js/app.3dec4d761531d1e7fe8c.hot-update.js",
    "/js/app.4c3e7b088125aa9af402.hot-update.js": "/js/app.4c3e7b088125aa9af402.hot-update.js",
    "/js/app.ae0a7ecf17824cccd2b6.hot-update.js": "/js/app.ae0a7ecf17824cccd2b6.hot-update.js",
    "/js/app.21c2c3a6f05d7060730b.hot-update.js": "/js/app.21c2c3a6f05d7060730b.hot-update.js",
    "/js/app.42b8d62be267092ff7f5.hot-update.js": "/js/app.42b8d62be267092ff7f5.hot-update.js",
    "/js/app.68a669c69b42f5affed1.hot-update.js": "/js/app.68a669c69b42f5affed1.hot-update.js",
    "/js/app.abb4c4105b0169bd6338.hot-update.js": "/js/app.abb4c4105b0169bd6338.hot-update.js",
    "/js/app.0477e081fdaaf5ae0046.hot-update.js": "/js/app.0477e081fdaaf5ae0046.hot-update.js",
    "/js/app.d02d0a514637994028f8.hot-update.js": "/js/app.d02d0a514637994028f8.hot-update.js",
    "/js/app.d9617c8c6c2e8fd33f0b.hot-update.js": "/js/app.d9617c8c6c2e8fd33f0b.hot-update.js",
    "/js/app.712753cacb7d3d67185f.hot-update.js": "/js/app.712753cacb7d3d67185f.hot-update.js",
    "/js/app.8ca7033acde2cfecf6cf.hot-update.js": "/js/app.8ca7033acde2cfecf6cf.hot-update.js",
    "/js/app.7de28304dc90c3da30c3.hot-update.js": "/js/app.7de28304dc90c3da30c3.hot-update.js",
    "/js/app.8d952983183714570a7d.hot-update.js": "/js/app.8d952983183714570a7d.hot-update.js",
    "/js/app.d6b336685de2ea562bf0.hot-update.js": "/js/app.d6b336685de2ea562bf0.hot-update.js",
    "/js/app.3219557aaad9b6c41cac.hot-update.js": "/js/app.3219557aaad9b6c41cac.hot-update.js",
    "/js/app.876d2e9529846c357952.hot-update.js": "/js/app.876d2e9529846c357952.hot-update.js",
    "/js/app.5f03bb079f4e2e974a02.hot-update.js": "/js/app.5f03bb079f4e2e974a02.hot-update.js",
    "/js/app.9aef01723a2b5600602d.hot-update.js": "/js/app.9aef01723a2b5600602d.hot-update.js",
    "/js/app.599182972eb5038ec0ad.hot-update.js": "/js/app.599182972eb5038ec0ad.hot-update.js",
    "/js/app.b764bd23651a0fbe49dd.hot-update.js": "/js/app.b764bd23651a0fbe49dd.hot-update.js",
    "/js/app.f3d5a5676c271eda0dec.hot-update.js": "/js/app.f3d5a5676c271eda0dec.hot-update.js",
    "/js/app.2e5d422fb326e5ae42d9.hot-update.js": "/js/app.2e5d422fb326e5ae42d9.hot-update.js",
    "/js/app.2685878c0c14a5b732c4.hot-update.js": "/js/app.2685878c0c14a5b732c4.hot-update.js",
    "/js/app.9967f3146f8af0afef5b.hot-update.js": "/js/app.9967f3146f8af0afef5b.hot-update.js",
    "/js/app.b22e22936acb4e1b89a6.hot-update.js": "/js/app.b22e22936acb4e1b89a6.hot-update.js",
    "/js/app.7d630229b61f19830e03.hot-update.js": "/js/app.7d630229b61f19830e03.hot-update.js",
    "/js/app.307c004aa0867e8d93ee.hot-update.js": "/js/app.307c004aa0867e8d93ee.hot-update.js",
    "/js/app.a6467bb44e3b2cdde319.hot-update.js": "/js/app.a6467bb44e3b2cdde319.hot-update.js",
    "/js/app.7fd58d20134ac5630579.hot-update.js": "/js/app.7fd58d20134ac5630579.hot-update.js",
    "/js/app.392eb300c8a7952dd590.hot-update.js": "/js/app.392eb300c8a7952dd590.hot-update.js",
    "/js/app.da1418bfaed24e12509a.hot-update.js": "/js/app.da1418bfaed24e12509a.hot-update.js",
    "/js/app.71b33cb86ac6e3fb2e18.hot-update.js": "/js/app.71b33cb86ac6e3fb2e18.hot-update.js",
    "/js/app.e4e2327fed99ca24e07e.hot-update.js": "/js/app.e4e2327fed99ca24e07e.hot-update.js",
    "/js/app.abee91d05161131940d1.hot-update.js": "/js/app.abee91d05161131940d1.hot-update.js",
    "/js/app.2f7e71e08b473c6c8d1b.hot-update.js": "/js/app.2f7e71e08b473c6c8d1b.hot-update.js",
    "/js/app.237204dafee4a9e2e67a.hot-update.js": "/js/app.237204dafee4a9e2e67a.hot-update.js",
    "/js/app.216a5eb15d56316dbb97.hot-update.js": "/js/app.216a5eb15d56316dbb97.hot-update.js",
    "/js/app.07e63603392585eb2c2b.hot-update.js": "/js/app.07e63603392585eb2c2b.hot-update.js",
    "/js/app.87f9999932e822399f58.hot-update.js": "/js/app.87f9999932e822399f58.hot-update.js",
    "/js/app.5516f460c6338207add8.hot-update.js": "/js/app.5516f460c6338207add8.hot-update.js",
    "/js/app.485af90ee99a4e1a8dc8.hot-update.js": "/js/app.485af90ee99a4e1a8dc8.hot-update.js",
    "/js/app.56ff53b7bc8b75f3d226.hot-update.js": "/js/app.56ff53b7bc8b75f3d226.hot-update.js",
    "/js/app.1789d023f715d6b0bdb2.hot-update.js": "/js/app.1789d023f715d6b0bdb2.hot-update.js",
    "/js/app.6175e1bd57d987b32241.hot-update.js": "/js/app.6175e1bd57d987b32241.hot-update.js",
    "/js/app.b01244926236457598f8.hot-update.js": "/js/app.b01244926236457598f8.hot-update.js",
    "/js/app.a1dbd7f86a4ba6b7abcb.hot-update.js": "/js/app.a1dbd7f86a4ba6b7abcb.hot-update.js",
    "/js/app.f8e68888db961185831b.hot-update.js": "/js/app.f8e68888db961185831b.hot-update.js",
    "/js/app.02e4bef9160c3d359abc.hot-update.js": "/js/app.02e4bef9160c3d359abc.hot-update.js",
    "/js/app.fe7a81b15a78e410a7d7.hot-update.js": "/js/app.fe7a81b15a78e410a7d7.hot-update.js",
    "/js/app.cec7a2690255b8dacc45.hot-update.js": "/js/app.cec7a2690255b8dacc45.hot-update.js",
    "/js/app.6e397429314cf37f4685.hot-update.js": "/js/app.6e397429314cf37f4685.hot-update.js",
    "/js/app.210c5d9f6b75dce36ff4.hot-update.js": "/js/app.210c5d9f6b75dce36ff4.hot-update.js",
    "/js/app.72ec7ebc7622c681a42f.hot-update.js": "/js/app.72ec7ebc7622c681a42f.hot-update.js",
    "/js/app.09d954740d6f3c205855.hot-update.js": "/js/app.09d954740d6f3c205855.hot-update.js",
    "/js/app.5a0549cf68a5ec985541.hot-update.js": "/js/app.5a0549cf68a5ec985541.hot-update.js",
    "/js/app.a3212caa622b8dc52ed5.hot-update.js": "/js/app.a3212caa622b8dc52ed5.hot-update.js",
    "/js/app.ca0e280cd2290a61452c.hot-update.js": "/js/app.ca0e280cd2290a61452c.hot-update.js",
    "/js/app.ac7470d8c27c94690bf8.hot-update.js": "/js/app.ac7470d8c27c94690bf8.hot-update.js",
    "/js/app.f51191604cd482c031a5.hot-update.js": "/js/app.f51191604cd482c031a5.hot-update.js",
    "/js/app.5d2d81827f08ebd1df7b.hot-update.js": "/js/app.5d2d81827f08ebd1df7b.hot-update.js",
    "/js/app.94149f811be66f9350f3.hot-update.js": "/js/app.94149f811be66f9350f3.hot-update.js",
    "/js/app.2da087bdd5d3c169632c.hot-update.js": "/js/app.2da087bdd5d3c169632c.hot-update.js",
    "/js/app.a6f17841fd426ed715a5.hot-update.js": "/js/app.a6f17841fd426ed715a5.hot-update.js",
    "/js/app.d2edf5b275b50937ba0d.hot-update.js": "/js/app.d2edf5b275b50937ba0d.hot-update.js",
    "/js/app.60fd0310be75eab92bcc.hot-update.js": "/js/app.60fd0310be75eab92bcc.hot-update.js",
    "/js/app.644cfa9f1953805a9e09.hot-update.js": "/js/app.644cfa9f1953805a9e09.hot-update.js",
    "/js/app.5a007b5ad43a9ed42bda.hot-update.js": "/js/app.5a007b5ad43a9ed42bda.hot-update.js",
    "/js/app.8b819e1ab4b97ed194bf.hot-update.js": "/js/app.8b819e1ab4b97ed194bf.hot-update.js",
    "/js/app.c71cdef94fc48c065521.hot-update.js": "/js/app.c71cdef94fc48c065521.hot-update.js",
    "/js/app.8f3b40b04af7e5c6c0b3.hot-update.js": "/js/app.8f3b40b04af7e5c6c0b3.hot-update.js",
    "/js/app.683b411e76132ad0986f.hot-update.js": "/js/app.683b411e76132ad0986f.hot-update.js",
    "/js/app.5af711cb2e50a080a278.hot-update.js": "/js/app.5af711cb2e50a080a278.hot-update.js",
    "/js/app.e73cda3c937aa1a91cfc.hot-update.js": "/js/app.e73cda3c937aa1a91cfc.hot-update.js",
    "/js/app.6705bb0ebe8c5fd8dbab.hot-update.js": "/js/app.6705bb0ebe8c5fd8dbab.hot-update.js",
    "/js/app.3e3f0e66275064d14a8e.hot-update.js": "/js/app.3e3f0e66275064d14a8e.hot-update.js",
    "/js/app.5974cf401657cf74efbb.hot-update.js": "/js/app.5974cf401657cf74efbb.hot-update.js",
    "/js/app.74944d699b473d2689d3.hot-update.js": "/js/app.74944d699b473d2689d3.hot-update.js",
    "/js/app.5017428396de1da48b83.hot-update.js": "/js/app.5017428396de1da48b83.hot-update.js",
    "/js/app.5f0daa2a2f01f96a852d.hot-update.js": "/js/app.5f0daa2a2f01f96a852d.hot-update.js",
    "/js/app.856c9d9d8d2dc013cc7e.hot-update.js": "/js/app.856c9d9d8d2dc013cc7e.hot-update.js",
    "/js/app.55a4b20712e5588b1fe4.hot-update.js": "/js/app.55a4b20712e5588b1fe4.hot-update.js",
    "/js/app.7ecfea8442b07495765b.hot-update.js": "/js/app.7ecfea8442b07495765b.hot-update.js",
    "/js/app.01bb403d135d68d3cb8b.hot-update.js": "/js/app.01bb403d135d68d3cb8b.hot-update.js",
    "/js/app.716533a1323c372a3ff4.hot-update.js": "/js/app.716533a1323c372a3ff4.hot-update.js",
    "/js/app.a29eb848e613a2f976fb.hot-update.js": "/js/app.a29eb848e613a2f976fb.hot-update.js",
    "/js/app.dfa557a16d889987bb6a.hot-update.js": "/js/app.dfa557a16d889987bb6a.hot-update.js",
    "/js/app.f58984dc76e434d344a7.hot-update.js": "/js/app.f58984dc76e434d344a7.hot-update.js",
    "/js/app.ee29aaa88d987771fe81.hot-update.js": "/js/app.ee29aaa88d987771fe81.hot-update.js",
    "/js/app.e255d28b68f1e8500277.hot-update.js": "/js/app.e255d28b68f1e8500277.hot-update.js",
    "/js/app.07472660bee79a48b670.hot-update.js": "/js/app.07472660bee79a48b670.hot-update.js",
    "/js/app.3a6b84b42686baf5c68a.hot-update.js": "/js/app.3a6b84b42686baf5c68a.hot-update.js",
    "/js/app.4c13694e22bef49cf43d.hot-update.js": "/js/app.4c13694e22bef49cf43d.hot-update.js",
    "/js/app.02491f963c5938eada3e.hot-update.js": "/js/app.02491f963c5938eada3e.hot-update.js",
    "/js/app.c529f66a8057db32c58d.hot-update.js": "/js/app.c529f66a8057db32c58d.hot-update.js",
    "/js/app.c7141c48501fc5a5a8d3.hot-update.js": "/js/app.c7141c48501fc5a5a8d3.hot-update.js",
    "/js/app.70cb2f286251bb48481c.hot-update.js": "/js/app.70cb2f286251bb48481c.hot-update.js",
    "/js/app.a99a2fbd71b494884466.hot-update.js": "/js/app.a99a2fbd71b494884466.hot-update.js",
    "/js/app.be4dd9e46161a0b22f85.hot-update.js": "/js/app.be4dd9e46161a0b22f85.hot-update.js",
    "/js/app.d651185a0e0162aac580.hot-update.js": "/js/app.d651185a0e0162aac580.hot-update.js",
    "/js/app.e4b4b2f566e541834d2b.hot-update.js": "/js/app.e4b4b2f566e541834d2b.hot-update.js",
    "/js/app.5a1c26673eb00769259e.hot-update.js": "/js/app.5a1c26673eb00769259e.hot-update.js",
    "/js/app.9d571d2a15eae7dcb943.hot-update.js": "/js/app.9d571d2a15eae7dcb943.hot-update.js",
    "/js/app.b9040a7fd6b12762ac7a.hot-update.js": "/js/app.b9040a7fd6b12762ac7a.hot-update.js",
    "/js/app.bdaaf8a2faac667f4199.hot-update.js": "/js/app.bdaaf8a2faac667f4199.hot-update.js",
    "/js/app.dd1185c0db947c77107d.hot-update.js": "/js/app.dd1185c0db947c77107d.hot-update.js",
    "/js/app.22bf446ae3e3621ee8b9.hot-update.js": "/js/app.22bf446ae3e3621ee8b9.hot-update.js",
    "/js/app.7c0315a388a28b6f4b09.hot-update.js": "/js/app.7c0315a388a28b6f4b09.hot-update.js",
    "/js/app.f6c20383ce2ab4b5ef7c.hot-update.js": "/js/app.f6c20383ce2ab4b5ef7c.hot-update.js",
    "/js/app.3d650aafa679a359a232.hot-update.js": "/js/app.3d650aafa679a359a232.hot-update.js",
    "/js/app.9cd5cb40ef3eb7a4979c.hot-update.js": "/js/app.9cd5cb40ef3eb7a4979c.hot-update.js",
    "/js/app.723e8f055b74b87801b9.hot-update.js": "/js/app.723e8f055b74b87801b9.hot-update.js",
    "/js/app.fe583806692449a8fee2.hot-update.js": "/js/app.fe583806692449a8fee2.hot-update.js",
    "/js/app.2adff3a76f2e702a65a1.hot-update.js": "/js/app.2adff3a76f2e702a65a1.hot-update.js",
    "/js/app.e5e06f8baa3095af1540.hot-update.js": "/js/app.e5e06f8baa3095af1540.hot-update.js",
    "/js/app.5a0255ef6828e1713419.hot-update.js": "/js/app.5a0255ef6828e1713419.hot-update.js",
    "/js/app.f32e3915182fea630677.hot-update.js": "/js/app.f32e3915182fea630677.hot-update.js",
    "/js/app.253f366e9d84844d7986.hot-update.js": "/js/app.253f366e9d84844d7986.hot-update.js",
    "/js/app.87fb24ab7e51a695d09c.hot-update.js": "/js/app.87fb24ab7e51a695d09c.hot-update.js",
    "/js/app.7f0558cb0b4e19a7f64b.hot-update.js": "/js/app.7f0558cb0b4e19a7f64b.hot-update.js",
    "/js/app.c6c0a6a63a3531337e56.hot-update.js": "/js/app.c6c0a6a63a3531337e56.hot-update.js",
    "/js/app.ca58a7d65c69212b8a0f.hot-update.js": "/js/app.ca58a7d65c69212b8a0f.hot-update.js",
    "/js/app.23807c8e479b2978fb59.hot-update.js": "/js/app.23807c8e479b2978fb59.hot-update.js",
    "/js/app.8fabfccb4a6523ab8640.hot-update.js": "/js/app.8fabfccb4a6523ab8640.hot-update.js",
    "/js/app.e3e3ddc5302fb9208c22.hot-update.js": "/js/app.e3e3ddc5302fb9208c22.hot-update.js",
    "/js/app.9be7678936bc20c38124.hot-update.js": "/js/app.9be7678936bc20c38124.hot-update.js",
    "/js/app.b1a1c8a0f7e65cd15b12.hot-update.js": "/js/app.b1a1c8a0f7e65cd15b12.hot-update.js",
    "/js/app.22443ebd71a88487f207.hot-update.js": "/js/app.22443ebd71a88487f207.hot-update.js",
    "/js/app.c2ad59b8a01c3bdd2201.hot-update.js": "/js/app.c2ad59b8a01c3bdd2201.hot-update.js",
    "/js/app.2b9b8ee2dff51b76008d.hot-update.js": "/js/app.2b9b8ee2dff51b76008d.hot-update.js",
    "/js/app.3287249584f64e2e9a95.hot-update.js": "/js/app.3287249584f64e2e9a95.hot-update.js",
    "/js/app.b5d84a8855f8489b0afd.hot-update.js": "/js/app.b5d84a8855f8489b0afd.hot-update.js",
    "/js/app.cbc26347e5e4a316028b.hot-update.js": "/js/app.cbc26347e5e4a316028b.hot-update.js",
    "/js/app.bc74f9677c2d8764abd5.hot-update.js": "/js/app.bc74f9677c2d8764abd5.hot-update.js",
    "/js/app.a23b95a0d3d31719c926.hot-update.js": "/js/app.a23b95a0d3d31719c926.hot-update.js",
    "/js/app.3a66b51d04a4e2bb3c38.hot-update.js": "/js/app.3a66b51d04a4e2bb3c38.hot-update.js",
    "/js/app.83d174fb97ea8caa2e89.hot-update.js": "/js/app.83d174fb97ea8caa2e89.hot-update.js",
    "/js/app.ce6b5cbf39fd1b7d99c2.hot-update.js": "/js/app.ce6b5cbf39fd1b7d99c2.hot-update.js",
    "/js/app.3c05c60a8ad8b768f3cf.hot-update.js": "/js/app.3c05c60a8ad8b768f3cf.hot-update.js",
    "/js/app.99574317807589472ad4.hot-update.js": "/js/app.99574317807589472ad4.hot-update.js",
    "/js/app.886936ca0d39764e55d7.hot-update.js": "/js/app.886936ca0d39764e55d7.hot-update.js",
    "/js/app.a3f698fcee3622b3e3af.hot-update.js": "/js/app.a3f698fcee3622b3e3af.hot-update.js",
    "/js/app.f2693b77d582edc0df76.hot-update.js": "/js/app.f2693b77d582edc0df76.hot-update.js",
    "/js/app.a479d2f9f0d390125a22.hot-update.js": "/js/app.a479d2f9f0d390125a22.hot-update.js",
    "/js/app.13367690b72cb144d3ad.hot-update.js": "/js/app.13367690b72cb144d3ad.hot-update.js",
    "/js/app.561a03cf7b7c5092cd4f.hot-update.js": "/js/app.561a03cf7b7c5092cd4f.hot-update.js",
    "/js/app.c09e6c72294f34108599.hot-update.js": "/js/app.c09e6c72294f34108599.hot-update.js",
    "/js/app.d9eb6541fc6799837848.hot-update.js": "/js/app.d9eb6541fc6799837848.hot-update.js",
    "/js/app.b8cfb2d6d2aaccb5c2fa.hot-update.js": "/js/app.b8cfb2d6d2aaccb5c2fa.hot-update.js",
    "/js/app.0e688dd79c755f19c536.hot-update.js": "/js/app.0e688dd79c755f19c536.hot-update.js",
    "/js/app.658521228913860e8cde.hot-update.js": "/js/app.658521228913860e8cde.hot-update.js",
    "/js/app.c1933af80a04a2d96af7.hot-update.js": "/js/app.c1933af80a04a2d96af7.hot-update.js",
    "/js/app.0092e19cdaaaf4c2ba17.hot-update.js": "/js/app.0092e19cdaaaf4c2ba17.hot-update.js",
    "/js/app.c6ff48867fe3f9877c63.hot-update.js": "/js/app.c6ff48867fe3f9877c63.hot-update.js",
    "/js/app.fa209bfd8785034a7276.hot-update.js": "/js/app.fa209bfd8785034a7276.hot-update.js",
    "/js/app.026603bfe8296b81dbf4.hot-update.js": "/js/app.026603bfe8296b81dbf4.hot-update.js",
    "/js/app.91adb606c23a257a39e2.hot-update.js": "/js/app.91adb606c23a257a39e2.hot-update.js",
    "/js/app.54c844ce5c0b83f30817.hot-update.js": "/js/app.54c844ce5c0b83f30817.hot-update.js",
    "/js/app.358dcfb05c674516c80a.hot-update.js": "/js/app.358dcfb05c674516c80a.hot-update.js",
    "/js/app.4ef61f88b52ae62d53dc.hot-update.js": "/js/app.4ef61f88b52ae62d53dc.hot-update.js",
    "/js/app.7c9cec7bafdc930806a7.hot-update.js": "/js/app.7c9cec7bafdc930806a7.hot-update.js",
    "/js/app.3202b281307ee3f9eacc.hot-update.js": "/js/app.3202b281307ee3f9eacc.hot-update.js",
    "/js/app.afc64495911a9fc87bc0.hot-update.js": "/js/app.afc64495911a9fc87bc0.hot-update.js",
    "/js/app.3211c86ef114cedf84d0.hot-update.js": "/js/app.3211c86ef114cedf84d0.hot-update.js",
    "/js/app.1bd6bdbce88ca36d21e3.hot-update.js": "/js/app.1bd6bdbce88ca36d21e3.hot-update.js",
    "/js/app.07598bd32ee67e6c2dbd.hot-update.js": "/js/app.07598bd32ee67e6c2dbd.hot-update.js",
    "/js/app.833e1c6d18b6a38fd38f.hot-update.js": "/js/app.833e1c6d18b6a38fd38f.hot-update.js",
    "/js/app.bb3c4ef2b288ce55ad72.hot-update.js": "/js/app.bb3c4ef2b288ce55ad72.hot-update.js",
    "/js/app.b280e70049047fb325cd.hot-update.js": "/js/app.b280e70049047fb325cd.hot-update.js",
    "/js/app.f5f6c1bce28e61d63ba9.hot-update.js": "/js/app.f5f6c1bce28e61d63ba9.hot-update.js",
    "/js/app.2528f7889f287abccd42.hot-update.js": "/js/app.2528f7889f287abccd42.hot-update.js",
    "/js/app.e2183eeb6307ac2c6981.hot-update.js": "/js/app.e2183eeb6307ac2c6981.hot-update.js",
    "/js/app.48de5e2ec3fd89342d5a.hot-update.js": "/js/app.48de5e2ec3fd89342d5a.hot-update.js",
    "/js/app.d0edcb4d71cbc3141465.hot-update.js": "/js/app.d0edcb4d71cbc3141465.hot-update.js",
    "/js/app.de0cfab808fd3bbe1cf7.hot-update.js": "/js/app.de0cfab808fd3bbe1cf7.hot-update.js",
    "/js/app.ba34b3b84960b08759cf.hot-update.js": "/js/app.ba34b3b84960b08759cf.hot-update.js",
    "/js/app.870304aeaba90664fab2.hot-update.js": "/js/app.870304aeaba90664fab2.hot-update.js",
    "/js/app.41ba05adc3e3161b35b2.hot-update.js": "/js/app.41ba05adc3e3161b35b2.hot-update.js",
    "/js/app.28e54b6454b25c00baa7.hot-update.js": "/js/app.28e54b6454b25c00baa7.hot-update.js",
    "/js/app.de9b3c2be4650632832a.hot-update.js": "/js/app.de9b3c2be4650632832a.hot-update.js",
    "/js/app.ebba1d5767bdb550bab9.hot-update.js": "/js/app.ebba1d5767bdb550bab9.hot-update.js",
    "/js/app.41e91038bb19c87472ad.hot-update.js": "/js/app.41e91038bb19c87472ad.hot-update.js",
    "/js/app.185a43732530bbcde85e.hot-update.js": "/js/app.185a43732530bbcde85e.hot-update.js",
    "/js/app.e7913081293726d8c7b0.hot-update.js": "/js/app.e7913081293726d8c7b0.hot-update.js",
    "/js/app.e9ff49fbcbe5ea446d67.hot-update.js": "/js/app.e9ff49fbcbe5ea446d67.hot-update.js",
    "/js/app.e84804701e5252663312.hot-update.js": "/js/app.e84804701e5252663312.hot-update.js",
    "/js/app.a53df90a4fdd06ad845b.hot-update.js": "/js/app.a53df90a4fdd06ad845b.hot-update.js",
    "/js/app.3d1a16a805c3b0f270d2.hot-update.js": "/js/app.3d1a16a805c3b0f270d2.hot-update.js",
    "/js/app.2e0109ed2551b32d9cae.hot-update.js": "/js/app.2e0109ed2551b32d9cae.hot-update.js",
    "/js/app.8418fbd3631f32b2da8a.hot-update.js": "/js/app.8418fbd3631f32b2da8a.hot-update.js",
    "/js/app.2a40c5f8615dbe5a5383.hot-update.js": "/js/app.2a40c5f8615dbe5a5383.hot-update.js",
    "/js/app.6002c26a85d9100de6be.hot-update.js": "/js/app.6002c26a85d9100de6be.hot-update.js",
    "/js/app.950f51b81ad0ff6e6629.hot-update.js": "/js/app.950f51b81ad0ff6e6629.hot-update.js",
    "/js/app.2498b4f22a316dac8044.hot-update.js": "/js/app.2498b4f22a316dac8044.hot-update.js",
    "/js/app.76b480ec1bb4000f13e1.hot-update.js": "/js/app.76b480ec1bb4000f13e1.hot-update.js",
    "/js/app.84349239818a3744130f.hot-update.js": "/js/app.84349239818a3744130f.hot-update.js",
    "/js/app.404ac524d37a73b814ad.hot-update.js": "/js/app.404ac524d37a73b814ad.hot-update.js",
    "/js/app.67255dc85cff0dd5244f.hot-update.js": "/js/app.67255dc85cff0dd5244f.hot-update.js",
    "/js/app.4ed9eff0f8f9935c0978.hot-update.js": "/js/app.4ed9eff0f8f9935c0978.hot-update.js",
    "/js/app.88c54aae469371af0767.hot-update.js": "/js/app.88c54aae469371af0767.hot-update.js",
    "/js/app.1babc585275855b72973.hot-update.js": "/js/app.1babc585275855b72973.hot-update.js",
    "/js/app.02c998207f3b76157e54.hot-update.js": "/js/app.02c998207f3b76157e54.hot-update.js",
    "/js/app.871acf4426dc7438b25f.hot-update.js": "/js/app.871acf4426dc7438b25f.hot-update.js",
    "/js/app.8c13ed94763b5e8c44c1.hot-update.js": "/js/app.8c13ed94763b5e8c44c1.hot-update.js",
    "/js/app.15b67c42d46e306ac3d4.hot-update.js": "/js/app.15b67c42d46e306ac3d4.hot-update.js",
    "/js/app.23325e6e547890847600.hot-update.js": "/js/app.23325e6e547890847600.hot-update.js",
    "/js/app.f07746ce39b1ae29a1d9.hot-update.js": "/js/app.f07746ce39b1ae29a1d9.hot-update.js",
    "/js/app.d56f3e88192f4ac0c774.hot-update.js": "/js/app.d56f3e88192f4ac0c774.hot-update.js",
    "/js/app.0c4fe275454f02725d4e.hot-update.js": "/js/app.0c4fe275454f02725d4e.hot-update.js",
    "/js/app.0e4e018e12ef3d35fc1e.hot-update.js": "/js/app.0e4e018e12ef3d35fc1e.hot-update.js",
    "/js/app.3c47bcc72a6d0b8e74d4.hot-update.js": "/js/app.3c47bcc72a6d0b8e74d4.hot-update.js",
    "/js/app.6d459d79234c82dceab2.hot-update.js": "/js/app.6d459d79234c82dceab2.hot-update.js",
    "/js/app.35b5824f19d0cb2466f4.hot-update.js": "/js/app.35b5824f19d0cb2466f4.hot-update.js",
    "/js/app.71901ba697781e30518c.hot-update.js": "/js/app.71901ba697781e30518c.hot-update.js",
    "/js/app.4db823024cb95c39bc77.hot-update.js": "/js/app.4db823024cb95c39bc77.hot-update.js",
    "/js/app.f0f4f321a71ad9ea0c42.hot-update.js": "/js/app.f0f4f321a71ad9ea0c42.hot-update.js",
    "/js/app.6721d4819f9aa38d04ef.hot-update.js": "/js/app.6721d4819f9aa38d04ef.hot-update.js",
    "/js/app.713cb490a8fa025af95d.hot-update.js": "/js/app.713cb490a8fa025af95d.hot-update.js",
    "/js/app.7e7725913011f02df680.hot-update.js": "/js/app.7e7725913011f02df680.hot-update.js",
    "/js/app.87c65ae292f7d6a3cbf1.hot-update.js": "/js/app.87c65ae292f7d6a3cbf1.hot-update.js",
    "/js/app.54d61c71daff312f749a.hot-update.js": "/js/app.54d61c71daff312f749a.hot-update.js",
    "/js/app.80c25a490b473b100cbf.hot-update.js": "/js/app.80c25a490b473b100cbf.hot-update.js",
    "/js/app.c22ec472133d157bce3b.hot-update.js": "/js/app.c22ec472133d157bce3b.hot-update.js",
    "/js/app.0714501dda4d39dbe023.hot-update.js": "/js/app.0714501dda4d39dbe023.hot-update.js",
    "/js/app.c37ec6955acbdc8b4e89.hot-update.js": "/js/app.c37ec6955acbdc8b4e89.hot-update.js",
    "/js/app.62c2537a9067d4c27412.hot-update.js": "/js/app.62c2537a9067d4c27412.hot-update.js",
    "/js/app.ce03a6327123ad47b9fd.hot-update.js": "/js/app.ce03a6327123ad47b9fd.hot-update.js",
    "/js/app.896ce9fd971662312ca9.hot-update.js": "/js/app.896ce9fd971662312ca9.hot-update.js",
    "/js/app.1b6c835428cd4bc1fc9d.hot-update.js": "/js/app.1b6c835428cd4bc1fc9d.hot-update.js",
    "/js/app.b1e12387a1967f31aac0.hot-update.js": "/js/app.b1e12387a1967f31aac0.hot-update.js",
    "/js/app.5051752db2b30f78f868.hot-update.js": "/js/app.5051752db2b30f78f868.hot-update.js",
    "/js/app.3211514350685671944c.hot-update.js": "/js/app.3211514350685671944c.hot-update.js",
    "/js/app.eabaedc3eedba0640eb0.hot-update.js": "/js/app.eabaedc3eedba0640eb0.hot-update.js",
    "/js/app.5f87296081d1c172b86b.hot-update.js": "/js/app.5f87296081d1c172b86b.hot-update.js",
    "/js/app.63b8d61916252c0fecfd.hot-update.js": "/js/app.63b8d61916252c0fecfd.hot-update.js",
    "/js/app.20ef428736445c69c593.hot-update.js": "/js/app.20ef428736445c69c593.hot-update.js",
    "/js/app.05ded7e2718d9a117e65.hot-update.js": "/js/app.05ded7e2718d9a117e65.hot-update.js",
    "/js/app.745668557427de119148.hot-update.js": "/js/app.745668557427de119148.hot-update.js",
    "/js/app.238424bb4def4262f501.hot-update.js": "/js/app.238424bb4def4262f501.hot-update.js",
    "/js/app.b3bf1b160e714cf02f17.hot-update.js": "/js/app.b3bf1b160e714cf02f17.hot-update.js",
    "/js/app.180fc6fb2a1a2d6492ac.hot-update.js": "/js/app.180fc6fb2a1a2d6492ac.hot-update.js",
    "/js/app.667f8aa166deb95dd371.hot-update.js": "/js/app.667f8aa166deb95dd371.hot-update.js",
    "/js/app.7e4bf6390e86df7b523d.hot-update.js": "/js/app.7e4bf6390e86df7b523d.hot-update.js",
    "/js/app.f797f344ece69d907282.hot-update.js": "/js/app.f797f344ece69d907282.hot-update.js",
    "/js/app.8221d869b02cddd166e9.hot-update.js": "/js/app.8221d869b02cddd166e9.hot-update.js",
    "/js/app.81cf571996c5668db747.hot-update.js": "/js/app.81cf571996c5668db747.hot-update.js",
    "/js/app.b38365d0adb9573c0a78.hot-update.js": "/js/app.b38365d0adb9573c0a78.hot-update.js",
    "/js/app.6273a015b3b9f50df06f.hot-update.js": "/js/app.6273a015b3b9f50df06f.hot-update.js",
    "/js/app.75a915163d30ff82f605.hot-update.js": "/js/app.75a915163d30ff82f605.hot-update.js",
    "/js/app.ed3967db4033a02d840d.hot-update.js": "/js/app.ed3967db4033a02d840d.hot-update.js",
    "/js/app.345da3934c7a9e1c8655.hot-update.js": "/js/app.345da3934c7a9e1c8655.hot-update.js",
    "/js/app.dd94958f35b40ac40462.hot-update.js": "/js/app.dd94958f35b40ac40462.hot-update.js",
    "/js/app.a9779f29ca2da091e96b.hot-update.js": "/js/app.a9779f29ca2da091e96b.hot-update.js",
    "/js/app.b5e25f50660644b7bcab.hot-update.js": "/js/app.b5e25f50660644b7bcab.hot-update.js",
    "/js/app.4cc47633a08e265aba15.hot-update.js": "/js/app.4cc47633a08e265aba15.hot-update.js",
    "/js/app.1d3fcca7d9db6a49526d.hot-update.js": "/js/app.1d3fcca7d9db6a49526d.hot-update.js",
    "/js/app.524bb213449fcca5b88b.hot-update.js": "/js/app.524bb213449fcca5b88b.hot-update.js",
    "/js/app.f0f32ae78eed4986d6d2.hot-update.js": "/js/app.f0f32ae78eed4986d6d2.hot-update.js",
    "/js/app.5d801fd3d81fba0b7d78.hot-update.js": "/js/app.5d801fd3d81fba0b7d78.hot-update.js",
    "/js/app.43ef0178eec7e6719f55.hot-update.js": "/js/app.43ef0178eec7e6719f55.hot-update.js",
    "/js/app.ac3a054381abe2aa7edb.hot-update.js": "/js/app.ac3a054381abe2aa7edb.hot-update.js",
    "/js/app.649d0ff5daed6b3cb9c4.hot-update.js": "/js/app.649d0ff5daed6b3cb9c4.hot-update.js",
    "/js/app.d868cf7e7a28a45728f3.hot-update.js": "/js/app.d868cf7e7a28a45728f3.hot-update.js",
    "/js/app.e2b97df8837e23720045.hot-update.js": "/js/app.e2b97df8837e23720045.hot-update.js",
    "/js/app.b2f4f327af70a3788dd8.hot-update.js": "/js/app.b2f4f327af70a3788dd8.hot-update.js",
    "/js/app.9190a9c08c1d68b39f1c.hot-update.js": "/js/app.9190a9c08c1d68b39f1c.hot-update.js",
    "/js/app.656e925a35f6208a7d04.hot-update.js": "/js/app.656e925a35f6208a7d04.hot-update.js",
    "/js/app.589048af86d8de0e56b2.hot-update.js": "/js/app.589048af86d8de0e56b2.hot-update.js",
    "/js/app.ab43d6a7663b2dad8ccb.hot-update.js": "/js/app.ab43d6a7663b2dad8ccb.hot-update.js",
    "/js/app.1178cd3443522263fe60.hot-update.js": "/js/app.1178cd3443522263fe60.hot-update.js",
    "/js/app.a253a35d9d8e8c79a99d.hot-update.js": "/js/app.a253a35d9d8e8c79a99d.hot-update.js",
    "/js/app.9289d85fba7bdf9bf64e.hot-update.js": "/js/app.9289d85fba7bdf9bf64e.hot-update.js",
    "/js/app.cf6612593a2f88535af6.hot-update.js": "/js/app.cf6612593a2f88535af6.hot-update.js",
    "/js/app.717d814743fda23e5d27.hot-update.js": "/js/app.717d814743fda23e5d27.hot-update.js",
    "/js/app.d3a7deb5bf8dfa9c9d19.hot-update.js": "/js/app.d3a7deb5bf8dfa9c9d19.hot-update.js",
    "/js/app.2122cf4100c5b95ba52d.hot-update.js": "/js/app.2122cf4100c5b95ba52d.hot-update.js",
    "/js/app.67a2f679bc849fba6773.hot-update.js": "/js/app.67a2f679bc849fba6773.hot-update.js",
    "/js/app.f2284f0f7abded775ffd.hot-update.js": "/js/app.f2284f0f7abded775ffd.hot-update.js",
    "/js/app.f819de4957c3ef2093c0.hot-update.js": "/js/app.f819de4957c3ef2093c0.hot-update.js",
    "/js/app.b628d763359c0ed9c2d8.hot-update.js": "/js/app.b628d763359c0ed9c2d8.hot-update.js",
    "/js/app.5242c8cfad6cb358b841.hot-update.js": "/js/app.5242c8cfad6cb358b841.hot-update.js",
    "/js/app.cd5f7c5c0ce3332ae7f5.hot-update.js": "/js/app.cd5f7c5c0ce3332ae7f5.hot-update.js",
    "/js/app.60e3f8c62233732e5754.hot-update.js": "/js/app.60e3f8c62233732e5754.hot-update.js",
    "/js/app.59d0dba61e2cead924a8.hot-update.js": "/js/app.59d0dba61e2cead924a8.hot-update.js",
    "/js/app.ba0ad68bb791cfc37023.hot-update.js": "/js/app.ba0ad68bb791cfc37023.hot-update.js",
    "/js/app.f7e545b63287f15fb8e3.hot-update.js": "/js/app.f7e545b63287f15fb8e3.hot-update.js",
    "/js/app.d5415a312a70f6ffa461.hot-update.js": "/js/app.d5415a312a70f6ffa461.hot-update.js",
    "/js/app.fb889b6a8d24d09aa947.hot-update.js": "/js/app.fb889b6a8d24d09aa947.hot-update.js",
    "/js/app.209adf9405534288a953.hot-update.js": "/js/app.209adf9405534288a953.hot-update.js",
    "/js/app.10457852c26b5c587453.hot-update.js": "/js/app.10457852c26b5c587453.hot-update.js",
    "/js/app.967473b495a72e86a037.hot-update.js": "/js/app.967473b495a72e86a037.hot-update.js",
    "/js/app.f2e5aa66c64abac8c11d.hot-update.js": "/js/app.f2e5aa66c64abac8c11d.hot-update.js",
    "/js/app.fc8ee4976d9202defa44.hot-update.js": "/js/app.fc8ee4976d9202defa44.hot-update.js",
    "/js/app.526d6463b274b3eeb568.hot-update.js": "/js/app.526d6463b274b3eeb568.hot-update.js",
    "/js/app.7367c2cbb82cca951380.hot-update.js": "/js/app.7367c2cbb82cca951380.hot-update.js",
    "/js/app.3b5c2c4b3ab915f09a14.hot-update.js": "/js/app.3b5c2c4b3ab915f09a14.hot-update.js",
    "/js/app.b2031f9652e618608601.hot-update.js": "/js/app.b2031f9652e618608601.hot-update.js",
    "/js/app.b4f51f3d9cd36f5ad00b.hot-update.js": "/js/app.b4f51f3d9cd36f5ad00b.hot-update.js",
    "/js/app.580c24e9fb79751e4c2b.hot-update.js": "/js/app.580c24e9fb79751e4c2b.hot-update.js",
    "/js/app.4f43effeb9c770f3fd73.hot-update.js": "/js/app.4f43effeb9c770f3fd73.hot-update.js",
    "/js/app.8f5f60530b8b616b1fd3.hot-update.js": "/js/app.8f5f60530b8b616b1fd3.hot-update.js",
    "/js/app.589c759686245078ac6a.hot-update.js": "/js/app.589c759686245078ac6a.hot-update.js",
    "/js/app.d9f3c4a4a6a45f0071dc.hot-update.js": "/js/app.d9f3c4a4a6a45f0071dc.hot-update.js",
    "/js/app.65fc38c07e5b92394ff0.hot-update.js": "/js/app.65fc38c07e5b92394ff0.hot-update.js",
    "/js/app.bcc9c71242c6f9859fa2.hot-update.js": "/js/app.bcc9c71242c6f9859fa2.hot-update.js",
    "/js/app.67217f9a216955a020af.hot-update.js": "/js/app.67217f9a216955a020af.hot-update.js",
    "/js/app.c849f1ca7cff5d5a2202.hot-update.js": "/js/app.c849f1ca7cff5d5a2202.hot-update.js",
    "/js/app.cb5ee8e2baf9bd2a50a5.hot-update.js": "/js/app.cb5ee8e2baf9bd2a50a5.hot-update.js",
    "/js/app.8a56355131d77709b787.hot-update.js": "/js/app.8a56355131d77709b787.hot-update.js",
    "/js/app.424eaa6dea007868f210.hot-update.js": "/js/app.424eaa6dea007868f210.hot-update.js",
    "/js/app.7e1b67248bc805a9276d.hot-update.js": "/js/app.7e1b67248bc805a9276d.hot-update.js",
    "/js/app.a051f0d4017bc95c7299.hot-update.js": "/js/app.a051f0d4017bc95c7299.hot-update.js",
    "/js/app.89261d0f362b4d61663f.hot-update.js": "/js/app.89261d0f362b4d61663f.hot-update.js",
    "/js/app.176b56596e79f2b801a5.hot-update.js": "/js/app.176b56596e79f2b801a5.hot-update.js"
}
